mathieulareu_picsou/__init__.py
mathieulareu_picsou/picsou.py
mathieulareu_picsou-0.1.0.dist-info/METADATA
mathieulareu_picsou-0.1.0.dist-info/WHEEL
mathieulareu_picsou-0.1.0.dist-info/RECORD
