Metadata-Version: 2.1
Name: mathieulareu-picsou
Version: 0.1.0
Summary: 
Author: SoRKozZ
Author-email: flexop@ig2i.centralelille.fr
Requires-Python: ==3.10.11
Classifier: Programming Language :: Python :: 3
Requires-Dist: pillow (==10.1.0)
